numbars
