Metadata-Version: 2.1
Name: numbars
Version: 1.0.3
Summary: A python library that allows you to add, subtract, multiply, divide, and randomize numbers.
Home-page: 
Author: zelofi
License: MIT
Keywords: calculator,numbers,add,subract,multiply,divide,randomize
Classifier: Development Status :: 5 - Production/Stable
Classifier: Intended Audience :: Education
Classifier: Operating System :: Microsoft :: Windows :: Windows 10
Classifier: License :: OSI Approved :: MIT License
Classifier: Programming Language :: Python :: 3
License-File: LICENSE.txt
